sc2/__init__.py
sc2/action.py
sc2/bot_ai.py
sc2/cache.py
sc2/client.py
sc2/constants.py
sc2/controller.py
sc2/data.py
sc2/dicts/__init__.py
sc2/dicts/generic_redirect_abilities.py
sc2/dicts/unit_abilities.py
sc2/dicts/unit_research_abilities.py
sc2/dicts/unit_tech_alias.py
sc2/dicts/unit_train_build_abilities.py
sc2/dicts/unit_trained_from.py
sc2/dicts/unit_unit_alias.py
sc2/dicts/upgrade_researched_from.py
sc2/distances.py
sc2/expiring_dict.py
sc2/game_data.py
sc2/game_info.py
sc2/game_state.py
sc2/generate_ids.py
sc2/helpers/__init__.py
sc2/helpers/control_group.py
sc2/helpers/devtools.py
sc2/ids/__init__.py
sc2/ids/ability_id.py
sc2/ids/buff_id.py
sc2/ids/effect_id.py
sc2/ids/id_version.py
sc2/ids/unit_typeid.py
sc2/ids/upgrade_id.py
sc2/main.py
sc2/maps.py
sc2/observer_ai.py
sc2/paths.py
sc2/pixel_map.py
sc2/player.py
sc2/portconfig.py
sc2/position.py
sc2/power_source.py
sc2/protocol.py
sc2/proxy.py
sc2/renderer.py
sc2/sc2process.py
sc2/score.py
sc2/unit.py
sc2/unit_command.py
sc2/units.py
sc2/versions.py
sc2/wsl.py
apsc2-5.6.dist-info/LICENSE
apsc2-5.6.dist-info/WHEEL
apsc2-5.6.dist-info/METADATA
apsc2-5.6.dist-info/RECORD
