Metadata-Version: 2.1
Name: apsc2
Version: 5.6
Summary: A StarCraft II API Client for Python 3
Home-page: https://github.com/Burnysc2/python-sc2
License: MIT
Keywords: StarCraft,StarCraft 2,StarCraft II,AI,Bot
Author: BurnySc2
Author-email: gamingburny@gmail.com
Requires-Python: >=3.8,<3.11
Classifier: Development Status :: 4 - Beta
Classifier: Intended Audience :: Developers
Classifier: Intended Audience :: Education
Classifier: Intended Audience :: Science/Research
Classifier: License :: OSI Approved :: MIT License
Classifier: Operating System :: MacOS :: MacOS X
Classifier: Operating System :: Microsoft :: Windows
Classifier: Operating System :: POSIX :: Linux
Classifier: Programming Language :: Python :: 3
Classifier: Programming Language :: Python :: 3.10
Classifier: Programming Language :: Python :: 3.7
Classifier: Programming Language :: Python :: 3.8
Classifier: Programming Language :: Python :: 3.9
Classifier: Topic :: Games/Entertainment
Classifier: Topic :: Games/Entertainment :: Real Time Strategy
Classifier: Topic :: Scientific/Engineering
Classifier: Topic :: Scientific/Engineering :: Artificial Intelligence
Requires-Dist: aiohttp (>=3.7.4,<4.0.0)
Requires-Dist: loguru (>=0.6.0,<0.7.0)
Requires-Dist: mpyq (>=0.2.5,<0.3.0)
Requires-Dist: portpicker (>=1.4.0,<2.0.0)
Requires-Dist: protobuf (<4.0.0)
Requires-Dist: pyglet (>=1.5.21,<2.0.0)
Requires-Dist: s2clientprotocol (>=5.0.7,<6.0.0)
Requires-Dist: typing-extensions (>=4.1.1,<5.0.0)
Requires-Dist: win32-setctime (>=1.0.3,<2.0.0)
Project-URL: Documentation, https://burnysc2.github.io/python-sc2/docs/index.html
